{
  "name": "",
  "isOrdered": true,
  "folders": {
    "packages": {
      "name": "packages",
      "isOrdered": true,
      "folders": {
        "the-react-app": {
          "name": "the-react-app",
          "isOrdered": true,
          "folders": {},
          "files": {}
        },
        "the-react-scripts": {
          "name": "the-react-scripts",
          "isOrdered": true,
          "folders": {
            "bin": {
              "name": "bin",
              "isOrdered": true,
              "folders": {},
              "files": {}
            },
            "internals": {
              "name": "internals",
              "isOrdered": true,
              "folders": {},
              "files": {}
            },
            "samples": {
              "name": "samples",
              "isOrdered": true,
              "folders": {},
              "files": {}
            },
            "scripts": {
              "name": "scripts",
              "isOrdered": true,
              "folders": {},
              "files": {}
            },
            "server": {
              "name": "server",
              "isOrdered": true,
              "folders": {},
              "files": {}
            },
            "template": {
              "name": "template",
              "isOrdered": true,
              "folders": {
                "build": {
                  "name": "build",
                  "isOrdered": true,
                  "folders": {},
                  "files": {}
                },
                "docs": {
                  "name": "docs",
                  "isOrdered": true,
                  "folders": {},
                  "files": {}
                },
                "src": {
                  "name": "src",
                  "isOrdered": true,
                  "folders": {},
                  "files": {}
                }
              },
              "files": {
                "README": 0
              }
            },
            "utils": {
              "name": "utils",
              "isOrdered": true,
              "folders": {},
              "files": {}
            }
          },
          "files": {
            "LICENSE": 0,
            "README": 1
          }
        }
      },
      "files": {}
    }
  },
  "files": {
    "LICENSE": 0,
    "README": 1
  }
}